AUTHORS.rst
CONTRIBUTING.rst
HISTORY.rst
LICENSE
MANIFEST.in
README.rst
setup.cfg
setup.py
docs/Makefile
docs/api.rst
docs/authors.rst
docs/conf.py
docs/contributing.rst
docs/history.rst
docs/index.rst
docs/installation.rst
docs/make.bat
docs/readme.rst
docs/usage.rst
geezeo/__init__.py
geezeo/aggregation.py
geezeo/sdk.py
geezeo/util.py
geezeo.egg-info/PKG-INFO
geezeo.egg-info/SOURCES.txt
geezeo.egg-info/dependency_links.txt
geezeo.egg-info/not-zip-safe
geezeo.egg-info/requires.txt
geezeo.egg-info/top_level.txt
tests/__init__.py
tests/test_geezeo.py