Metadata-Version: 1.1
Name: geezeo
Version: 0.1.5
Summary: Connect to the Geezeo API.
Home-page: https://github.com/Geezeo/sdk-python
Author: Geezeo
Author-email: ddonna@amstonstudio.com
License: UNKNOWN
Keywords: geezeo
Platform: UNKNOWN
Classifier: Development Status :: 2 - Pre-Alpha
Classifier: Intended Audience :: Developers
Classifier: License :: OSI Approved :: ISC License (ISCL)
Classifier: Natural Language :: English
Classifier: Programming Language :: Python :: 2
Classifier: Programming Language :: Python :: 2.6
Classifier: Programming Language :: Python :: 2.7
Classifier: Programming Language :: Python :: 3
Classifier: Programming Language :: Python :: 3.3
Classifier: Programming Language :: Python :: 3.4
